{
    "legacy_addon_id": "",
    "title": "[VersoBit] Resource Threads",
    "description": "Synchronizes resource and resource-update discussion content during approval and deletion.",
    "version_id": 10000170,
    "version_string": "1.0.1",
    "dev": "VersoBit",
    "dev_url": "https://github.com/VersoBit",
    "faq_url": "",
    "support_url": "",
    "extra_urls": {
        "GitHub Repo": "https://github.com/Fellowsfilm/XF-ResourceThreads",
        "Report An Issue": "https://github.com/Fellowsfilm/XF-ResourceThreads/issues"
    },
    "require": [],
    "icon": "fa-sticky-note"
}
